Yowaimo/__init__.py
Yowaimo/Parsers/GogoParser.py
Yowaimo/Parsers/HanimeParser.py
Yowaimo/Parsers/KdramaParser.py
Yowaimo/Parsers/Manhwa18Parser.py
Yowaimo/Parsers/__init__.py
Yowaimo/Parsers/constants.py
Yowaimo/myCrypto/BaseCrypto.py
Yowaimo/myCrypto/GogoCrypto.py
Yowaimo/myCrypto/KdramaCrypto.py
Yowaimo/myCrypto/__init__.py
YowaiMo-0.0.1.dist-info/LICENCE
YowaiMo-0.0.1.dist-info/METADATA
YowaiMo-0.0.1.dist-info/WHEEL
YowaiMo-0.0.1.dist-info/top_level.txt
YowaiMo-0.0.1.dist-info/RECORD
