Metadata-Version: 2.1
Name: YowaiMo
Version: 0.0.1
Summary: A package for scrap anime/manga content
Author: Sree Krishna
License: UNKNOWN
Platform: UNKNOWN
Classifier: Programming Language :: Python :: 3
Classifier: License :: OSI Approved :: MIT License
Classifier: Operating System :: OS Independent
Requires-Python: >=3.6
License-File: LICENCE
Requires-Dist: Crypto
Requires-Dist: requests
Requires-Dist: beautifulsoup4
